sphinx_emoji_favicon/__init__.py
sphinx_emoji_favicon-0.2.dist-info/LICENSE
sphinx_emoji_favicon-0.2.dist-info/METADATA
sphinx_emoji_favicon-0.2.dist-info/WHEEL
sphinx_emoji_favicon-0.2.dist-info/top_level.txt
sphinx_emoji_favicon-0.2.dist-info/RECORD
