Metadata-Version: 2.1
Name: sphinx-emoji-favicon
Version: 0.2
Summary: A simple sphinx extension to add emoji favicons to html pages.
Home-page: https://github.com/DeepPSP/sphinx-emoji-favicon
Author: DeepPSP
Author-email: wenh06@gmail.com
License: MIT
Classifier: Programming Language :: Python
Classifier: Programming Language :: Python :: 3
Classifier: Programming Language :: Python :: 3.7
Classifier: Programming Language :: Python :: 3.8
Classifier: Programming Language :: Python :: 3.9
Classifier: Programming Language :: Python :: 3.10
Classifier: Programming Language :: Python :: 3.11
Classifier: License :: OSI Approved :: MIT License
Classifier: Operating System :: OS Independent
Requires-Python: >=3.7
License-File: LICENSE
Requires-Dist: sphinx
Requires-Dist: docutils
Requires-Dist: emoji
Provides-Extra: dev
Requires-Dist: tqdm ; extra == 'dev'
Requires-Dist: emoji ; extra == 'dev'
Provides-Extra: test
Requires-Dist: tqdm ; extra == 'test'
Requires-Dist: emoji ; extra == 'test'
